<graph version="v4.03" name="Starcraft Economy and Gameplay" author="" interval="1" timeMode="asynchronous" distributionMode="fixed speed" speed="100" actions="1" dice="D6" skill="" strategy="" multiplayer="" width="1000" height="700" numberOfRuns="100" visibleRuns="25" colorCoding="0">
  <connection type="Resource Connection" start="-1" end="-1" label="" position="0.5" color="Black" thickness="2">
    <point x="258" y="185"/>
    <point x="258" y="185"/>
  </connection>
  <connection type="Resource Connection" start="-1" end="-1" label="" position="0.5" color="Black" thickness="2">
    <point x="537" y="285"/>
    <point x="537" y="285"/>
  </connection>
  <connection type="Resource Connection" start="-1" end="-1" label="" position="0.5" color="Black" thickness="2">
    <point x="187" y="232"/>
    <point x="187" y="232"/>
  </connection>
  <connection type="Resource Connection" start="-1" end="-1" label="" position="0.5" color="Black" thickness="2">
    <point x="NaN" y="228"/>
    <point x="0" y="0"/>
  </connection>
  <connection type="Resource Connection" start="-1" end="-1" label="" position="0.5" color="Black" thickness="2">
    <point x="8" y="230"/>
    <point x="8" y="230"/>
  </connection>
  <connection type="Resource Connection" start="-1" end="-1" label="0" position="0.5" color="Black" thickness="2">
    <point x="0" y="0"/>
    <point x="0" y="0"/>
  </connection>
  <connection type="Resource Connection" start="-1" end="-1" label="0.5" position="0.5" color="Black" thickness="2">
    <point x="0" y="0"/>
    <point x="0" y="0"/>
  </connection>
  <connection type="Resource Connection" start="-1" end="-1" label="" position="0.5" color="Blue" thickness="2">
    <point x="484" y="282"/>
    <point x="484" y="282"/>
  </connection>
  <connection type="Resource Connection" start="42" end="48" label="0" position="0.5" color="Green" thickness="2"/>
  <connection type="State Connection" start="44" end="26" label="> 0" position="0.5" color="Black" thickness="2"/>
  <connection type="Resource Connection" start="16" end="44" label="+1" position="0.5" color="Black" thickness="2"/>
  <connection type="State Connection" start="17" end="38" label=">0" position="0.5" color="Black" thickness="2"/>
  <connection type="State Connection" start="17" end="39" label=">0" position="0.5" color="Black" thickness="2"/>
  <connection type="Resource Connection" start="45" end="26" label="" position="0.5" color="Black" thickness="2"/>
  <connection type="Resource Connection" start="26" end="45" label="" position="0.5" color="Black" thickness="2"/>
  <connection type="Resource Connection" start="23" end="28" label="5" position="0.5" color="Blue" thickness="2"/>
  <node symbol="Converter" x="186" y="241" color="Black" caption="Buy Assimilator" thickness="2" captionPos="0.25" activationMode="interactive" pullMode="pull all" actions="1" resourceColor="Black"/>
  <node symbol="Pool" x="256" y="324" color="Black" caption="Gateways" thickness="2" captionPos="0.25" activationMode="passive" pullMode="pull any" actions="1" resourceColor="Black" startingResources="0" maxResources="-1"/>
  <connection type="Resource Connection" start="22" end="46" label="8" position="0.5" color="Purple" thickness="2"/>
  <connection type="Resource Connection" start="32" end="17" label="" position="0.5" color="Red" thickness="2"/>
  <connection type="Resource Connection" start="21" end="45" label="" position="0.5" color="Black" thickness="2"/>
  <node symbol="Converter" x="188" y="164" color="Black" caption="Buy Worker" thickness="2" captionPos="0.25" activationMode="interactive" pullMode="pull all" actions="1" resourceColor="Black"/>
  <node symbol="Converter" x="180" y="400" color="Black" caption="Buy Pylon" thickness="2" captionPos="0.25" activationMode="interactive" pullMode="pull all" actions="1" resourceColor="Black"/>
  <node symbol="Pool" x="46" y="49" color="Blue" caption="Mineral Field" thickness="2" captionPos="0.25" activationMode="automatic" pullMode="push any" actions="1" resourceColor="Blue" startingResources="5000" maxResources="-1"/>
  <connection type="State Connection" start="45" end="15" label="+5" position="0.1" color="Black" thickness="2"/>
  <connection type="State Connection" start="26" end="8" label="+1" position="0.76" color="Black" thickness="2">
    <point x="109" y="133"/>
    <point x="79" y="235"/>
  </connection>
  <node symbol="Pool" x="264" y="36" color="Black" caption="Harvesters" thickness="2" captionPos="0.25" activationMode="interactive" pullMode="pull any" actions="1" resourceColor="Black" startingResources="0" maxResources="-1"/>
  <connection type="State Connection" start="46" end="21" label=">0" position="0.5" color="Black" thickness="2"/>
  <node symbol="Pool" x="45" y="144" color="Black" caption="Minerals" thickness="2" captionPos="0.25" activationMode="passive" pullMode="push all" actions="1" resourceColor="Blue" startingResources="50" maxResources="-1"/>
  <connection type="State Connection" start="46" end="39" label=">0" position="0.5" color="Purple" thickness="2"/>
  <connection type="State Connection" start="46" end="38" label=">0" position="0.5" color="Purple" thickness="2">
    <point x="377" y="266"/>
  </connection>
  <connection type="State Connection" start="47" end="46" label="-1" position="0.5" color="Black" thickness="2"/>
  <node symbol="Converter" x="183" y="322" color="Black" caption="Buy Gateway" thickness="2" captionPos="0.25" activationMode="interactive" pullMode="pull all" actions="1" resourceColor="Black"/>
  <connection type="Resource Connection" start="28" end="22" label="100" position="1" color="Blue" thickness="2"/>
  <connection type="Resource Connection" start="28" end="39" label="100" position="-0.99" color="Blue" thickness="2">
    <point x="80" y="320"/>
    <point x="262" y="280"/>
  </connection>
  <connection type="Resource Connection" start="28" end="16" label="75" position="0.96" color="Blue" thickness="2"/>
  <connection type="Resource Connection" start="28" end="21" label="50" position="0.88" color="Blue" thickness="2"/>
  <connection type="Resource Connection" start="28" end="32" label="150" position="1" color="Blue" thickness="2"/>
  <node symbol="Converter" x="345" y="303" color="Black" caption="Buy Dragoon" thickness="2" captionPos="0.19" activationMode="interactive" pullMode="pull all" actions="1" resourceColor="Black"/>
  <node symbol="Converter" x="343" y="217" color="Black" caption="Buy Zealot" thickness="2" captionPos="0.19" activationMode="interactive" pullMode="pull all" actions="1" resourceColor="Black"/>
  <connection type="Resource Connection" start="48" end="38" label="50" position="0.9500000000000001" color="Green" thickness="2">
    <point x="145" y="464"/>
    <point x="241" y="462"/>
    <point x="280" y="400"/>
  </connection>
  <connection type="Resource Connection" start="28" end="38" label="125" position="-1" color="Blue" thickness="2">
    <point x="80" y="335"/>
    <point x="264" y="378"/>
  </connection>
  <node symbol="Pool" x="32" y="270" color="Green" caption="Vespene Geyser" thickness="2" captionPos="0.25" activationMode="automatic" pullMode="push any" actions="1" resourceColor="Green" startingResources="2500" maxResources="-1"/>
  <connection type="Resource Connection" start="38" end="47" label="4" position="0.5" color="Black" thickness="2"/>
  <node symbol="Pool" x="262" y="170" color="Black" caption="Assimilators" thickness="2" captionPos="0.25" activationMode="passive" pullMode="pull any" actions="1" resourceColor="Black" startingResources="0" maxResources="-1"/>
  <node symbol="Pool" x="171" y="32" color="Black" caption="Miners" thickness="2" captionPos="0.25" activationMode="interactive" pullMode="pull any" actions="1" resourceColor="Black" startingResources="4" maxResources="-1"/>
  <node symbol="Pool" x="360" y="40" color="Purple" caption="Supply" thickness="2" captionPos="0.25" activationMode="passive" pullMode="push any" actions="1" resourceColor="Black" startingResources="8" maxResources="-1" tokenLimit="1"/>
  <node symbol="Pool" x="460" y="299" color="Black" caption="Forces" thickness="2" captionPos="0.25" activationMode="passive" pullMode="pull any" actions="1" resourceColor="Red" startingResources="0" maxResources="-1"/>
  <node symbol="Pool" x="27" y="395" color="Black" caption="Gas" thickness="2" captionPos="0.25" activationMode="passive" pullMode="pull any" actions="1" resourceColor="Green" startingResources="0" maxResources="-1"/>
  <connection type="Resource Connection" start="48" end="57" label="200" position="1" color="Green" thickness="2"/>
  <connection type="Resource Connection" start="28" end="57" label="250" position="0.92" color="Blue" thickness="2">
    <point x="80" y="360"/>
  </connection>
  <connection type="Resource Connection" start="57" end="52" label="" position="0.5" color="Black" thickness="2"/>
  <node symbol="Pool" x="252" y="574" color="Blue" caption="Tech" thickness="2" captionPos="0.25" activationMode="passive" pullMode="pull any" actions="1" resourceColor="Black" startingResources="0" maxResources="-1"/>
  <node symbol="Pool" x="240" y="455" color="Blue" caption="" thickness="2" captionPos="0.25" activationMode="passive" pullMode="pull any" actions="1" resourceColor="Black" startingResources="0" maxResources="-1"/>
  <connection type="Resource Connection" start="55" end="53" label="" position="0.5" color="Black" thickness="2"/>
  <node symbol="Converter" x="178" y="466" color="Black" caption="Buy Forge" thickness="2" captionPos="0.25" activationMode="interactive" pullMode="pull any" actions="1" resourceColor="Black"/>
  <connection type="Resource Connection" start="28" end="55" label="150" position="0.99" color="Black" thickness="2">
    <point x="80" y="360"/>
  </connection>
  <node symbol="Converter" x="179" y="544" color="Black" caption="Buy Tech" thickness="2" captionPos="0.25" activationMode="interactive" pullMode="pull all" actions="1" resourceColor="Black"/>
  <connection type="State Connection" start="53" end="57" label=">0" position="0.26" color="Blue" thickness="2"/>
  <connection type="State Connection" start="26" end="46" label="-1" position="0.5" color="Black" thickness="2"/>
  <connection type="State Connection" start="45" end="46" label="-1" position="-0.93" color="Black" thickness="2">
    <point x="259" y="5"/>
  </connection>
  <connection type="Resource Connection" start="39" end="47" label="2" position="0.5" color="Black" thickness="2"/>
  <connection type="State Connection" start="52" end="43" label="+1" position="0.5" color="Blue" thickness="2"/>
  <connection type="State Connection" start="52" end="61" label="+1" position="0.5" color="Blue" thickness="2">
    <point x="400" y="360"/>
  </connection>
</graph>